teke/__about__.py
teke/__init__.py
teke/connection.py
teke/response.py
teke/router.py
teke/utils.py
teke-0.0.1.dist-info/METADATA
teke-0.0.1.dist-info/WHEEL
teke-0.0.1.dist-info/licenses/LICENCE
teke-0.0.1.dist-info/RECORD
