Metadata-Version: 2.1
Name: teke
Version: 0.0.1
Summary: A lightweight ASGI framework
Project-URL: Documentation, https://github.com/mrkiura/teke
Project-URL: Issues, https://github.com/mrkiura/teke/issues
Project-URL: Source, https://github.com/mrkiura/teke
Author-email: Alex Kiura <kiuraalex@gmail.com>
Keywords: ASGI
Classifier: Development Status :: 4 - Beta
Classifier: Programming Language :: Python
Classifier: Programming Language :: Python :: 3.10
Classifier: Programming Language :: Python :: 3.11
Classifier: Programming Language :: Python :: Implementation :: CPython
Classifier: Programming Language :: Python :: Implementation :: PyPy
Requires-Python: >=3.10
Requires-Dist: anyio
Requires-Dist: pytest
Requires-Dist: pytest-cov
Requires-Dist: uvicorn
Requires-Dist: uvloop
Requires-Dist: werkzeug
